setup.py
src/Hatak_Formskit.egg-info/PKG-INFO
src/Hatak_Formskit.egg-info/SOURCES.txt
src/Hatak_Formskit.egg-info/dependency_links.txt
src/Hatak_Formskit.egg-info/namespace_packages.txt
src/Hatak_Formskit.egg-info/not-zip-safe
src/Hatak_Formskit.egg-info/requires.txt
src/Hatak_Formskit.egg-info/top_level.txt
src/haplugin/__init__.py
src/haplugin/formskit/__init__.py
src/haplugin/formskit/helpers.py
src/haplugin/formskit/models.py
src/haplugin/formskit/plugin.py
src/haplugin/formskit/testing.py
src/haplugin/formskit/tests/__init__.py