Metadata-Version: 1.0
Name: Hatak-Formskit
Version: 0.2.3.5
Summary: Formskit plugin for Hatak.
Home-page: UNKNOWN
Author: UNKNOWN
Author-email: UNKNOWN
License: Apache License 2.0
Platform: UNKNOWN
